cbsyst/__init__.py
cbsyst/boron.py
cbsyst/boron_isotopes.py
cbsyst/carbon.py
cbsyst/cbsyst.py
cbsyst/classes.py
cbsyst/helpers.py
cbsyst/CO2SYS/CO2SYS.m
cbsyst/docs/B_systematics.pdf
cbsyst/docs/Millero_2007_ChemicalReview.pdf
cbsyst/test_data/GLODAP_data/plot_GLODAPv2_comparison.py
cbsyst/test_data/GLODAP_data/Figures/DIC_comparison.png
cbsyst/test_data/GLODAP_data/Figures/TA_comparison.png
cbsyst/test_data/GLODAP_data/Figures/pH_comparison.png
tests/__init__.py
tests/check_vals.py
tests/test_boron.py
tests/test_boron_isotopes.py
tests/test_carbon.py
tests/test_cbsyst.py
tests/test_in_out.py
tests/test_palaeoB.py
tests/test_data/GLODAP_data/GLODAPv2_headers.txt
tests/test_data/GLODAP_data/Olsen_et_al-2016_GLODAPv2.pdf
tests/test_data/GLODAP_data/get_GLODAP_data.py
tests/test_data/GLODAP_data/plot_GLODAPv2_comparison.py
tests/test_data/GLODAP_data/Figures/DIC_comparison.png
tests/test_data/GLODAP_data/Figures/TA_comparison.png
tests/test_data/GLODAP_data/Figures/pH_comparison.png
tests/test_data/Lueker2000/Lueker2000_Table2.csv
tests/test_data/Lueker2000/Lueker2000_Table3.csv
tests/test_data/Lueker2000/Lueker_2000_MarineChemistry.pdf
tests/test_data/Orr2015/Orr_2015_Biogeosciences.pdf
tests/test_data/Orr2015/get_GLODAP_WOA_data.py
tests/test_data/Orr2015/plot_CO2SYS_comparison.py
cbsyst-0.4.9.dist-info/LICENCE.txt
cbsyst-0.4.9.dist-info/METADATA
cbsyst-0.4.9.dist-info/WHEEL
cbsyst-0.4.9.dist-info/top_level.txt
cbsyst-0.4.9.dist-info/zip-safe
cbsyst-0.4.9.dist-info/RECORD
