Metadata-Version: 2.1
Name: cbsyst
Version: 0.4.9
Summary: Tools for calculating ocean C and B chemistry.
Home-page: https://github.com/oscarbranson/cbsyst
Author: Oscar Branson
Author-email: ob266@cam.ac.uk
License: MIT
Keywords: science,chemistry,oceanography,carbon
Classifier: Programming Language :: Python :: 3 :: Only
Classifier: Intended Audience :: Science/Research
Requires-Python: >=3.7
License-File: LICENCE.txt
Requires-Dist: numpy >=1.13
Requires-Dist: scipy >=0.18
Requires-Dist: pandas >=0.19
Requires-Dist: uncertainties >=3.0
Requires-Dist: tqdm >=4.14
Requires-Dist: kgen >=0.2.0
